torch_adapters/__init__.py
torch_adapters/adapters/__init__.py
torch_adapters/adapters/adapter.py
torch_adapters/adapters/lora.py
torch_adapters/adapters/mixin.py
torch_adapters/adapters/prefix_tuning.py
torch_adapters/adapters/prompt_tuning.py
torch_adapters/utils.py
torch_adapters-0.0.6.dist-info/LICENSE
torch_adapters-0.0.6.dist-info/METADATA
torch_adapters-0.0.6.dist-info/WHEEL
torch_adapters-0.0.6.dist-info/RECORD
